kazam/__init__.py
kazam/app.py
kazam/instant.py
kazam/utils.py
kazam/version.py
kazam/__pycache__/__init__.cpython-310.pyc
kazam/__pycache__/__init__.cpython-312.pyc
kazam/__pycache__/__init__.cpython-37.pyc
kazam/__pycache__/__init__.cpython-38.pyc
kazam/__pycache__/app.cpython-310.pyc
kazam/__pycache__/app.cpython-312.pyc
kazam/__pycache__/app.cpython-37.pyc
kazam/__pycache__/app.cpython-38.pyc
kazam/__pycache__/utils.cpython-310.pyc
kazam/__pycache__/utils.cpython-312.pyc
kazam/__pycache__/utils.cpython-37.pyc
kazam/__pycache__/utils.cpython-38.pyc
kazam/__pycache__/version.cpython-310.pyc
kazam/__pycache__/version.cpython-312.pyc
kazam/__pycache__/version.cpython-37.pyc
kazam/__pycache__/version.cpython-38.pyc
kazam/backend/__init__.py
kazam/backend/config.py
kazam/backend/grabber.py
kazam/backend/gstreamer.py
kazam/backend/keypress.py
kazam/backend/listkeys-subprocess.py
kazam/backend/neoocr.py
kazam/backend/prefs.py
kazam/backend/utils.py
kazam/backend/webcam.py
kazam/backend/__pycache__/__init__.cpython-310.pyc
kazam/backend/__pycache__/__init__.cpython-312.pyc
kazam/backend/__pycache__/__init__.cpython-37.pyc
kazam/backend/__pycache__/__init__.cpython-38.pyc
kazam/backend/__pycache__/config.cpython-310.pyc
kazam/backend/__pycache__/config.cpython-312.pyc
kazam/backend/__pycache__/config.cpython-37.pyc
kazam/backend/__pycache__/config.cpython-38.pyc
kazam/backend/__pycache__/grabber.cpython-310.pyc
kazam/backend/__pycache__/grabber.cpython-312.pyc
kazam/backend/__pycache__/grabber.cpython-38.pyc
kazam/backend/__pycache__/gstreamer.cpython-310.pyc
kazam/backend/__pycache__/gstreamer.cpython-312.pyc
kazam/backend/__pycache__/gstreamer.cpython-38.pyc
kazam/backend/__pycache__/gwebcam.cpython-312.pyc
kazam/backend/__pycache__/gwebcam.cpython-38.pyc
kazam/backend/__pycache__/keypress.cpython-310.pyc
kazam/backend/__pycache__/keypress.cpython-312.pyc
kazam/backend/__pycache__/keypress.cpython-38.pyc
kazam/backend/__pycache__/neoocr.cpython-38.pyc
kazam-2.0.0.dist-info/AUTHORS
kazam-2.0.0.dist-info/COPYING
kazam-2.0.0.dist-info/COPYING.LGPL
kazam-2.0.0.dist-info/METADATA
kazam-2.0.0.dist-info/WHEEL
kazam-2.0.0.dist-info/top_level.txt
kazam-2.0.0.dist-info/RECORD
