Metadata-Version: 2.1
Name: kazam
Version: 2.0.0
Summary: A screencasting program created with design in mind.
Home-page: https://github.com/henrywoo/kazam
Author: Henry Fuheng Wu, David Klasinc
Author-email: wufuheng@gmail.com
License: Apache-2.0
Keywords: screencast screenshot capture audio sound video recorder kazam OCR webcam
Classifier: Development Status :: 5 - Production/Stable
Classifier: Environment :: X11 Applications :: GTK
Classifier: Intended Audience :: End Users/Desktop
Classifier: License :: OSI Approved :: GNU Library or Lesser General Public License (LGPL)
Classifier: Operating System :: POSIX :: Linux
Classifier: Programming Language :: Python
Classifier: Topic :: Multimedia :: Graphics :: Capture :: Screen Capture
Classifier: Topic :: Multimedia :: Sound/Audio :: Capture/Recording
Classifier: Topic :: Multimedia :: Video :: Capture
Classifier: Programming Language :: Python :: 3
Classifier: Programming Language :: Python :: 3.3
Classifier: Programming Language :: Python :: 3.4
Classifier: Programming Language :: Python :: 3.5
Classifier: Programming Language :: Python :: 3.6
Classifier: Programming Language :: Python :: 3.7
Classifier: Programming Language :: Python :: 3.8
Classifier: Programming Language :: Python :: 3.9
Classifier: Programming Language :: Python :: 3.10
Classifier: Programming Language :: Python :: 3.11
Classifier: Programming Language :: Python :: 3.12
License-File: COPYING
License-File: COPYING.LGPL
License-File: AUTHORS
Requires-Dist: cmake
Requires-Dist: distutils-extra-python
Requires-Dist: python-xlib
Requires-Dist: dbus-python
Requires-Dist: hiq-python
Requires-Dist: PyGObject
Requires-Dist: pyxdg
Requires-Dist: pycairo
Requires-Dist: distro
